coker/__init__.py
coker/algebra/__init__.py
coker/algebra/dimensions.py
coker/algebra/exceptions.py
coker/algebra/factories.py
coker/algebra/helpers.py
coker/algebra/kernel.py
coker/algebra/ops.py
coker/algebra/tensor.py
coker/backends/__init__.py
coker/backends/backend.py
coker/backends/casadi/__init__.py
coker/backends/casadi/casadi.py
coker/backends/casadi/optimiser.py
coker/backends/casadi/variational_solver.py
coker/backends/coker/__init__.py
coker/backends/coker/ast_preprocessing.py
coker/backends/coker/ast_rewriting.py
coker/backends/coker/core.py
coker/backends/coker/layers.py
coker/backends/coker/memory.py
coker/backends/coker/op_impl.py
coker/backends/coker/sparse_tensor.py
coker/backends/coker/tensor_contants.py
coker/backends/coker/weights.py
coker/backends/evaluator.py
coker/backends/jax/__init__.py
coker/backends/jax/optimiser.py
coker/backends/numpy/__init__.py
coker/backends/numpy/core.py
coker/backends/sympy/__init__.py
coker/dynamics/__init__.py
coker/dynamics/dynamical_system.py
coker/dynamics/transcription_helpers.py
coker/dynamics/types.py
coker/helpers.py
coker/toolkits/__init__.py
coker/toolkits/codesign/__init__.py
coker/toolkits/kinematics/__init__.py
coker/toolkits/kinematics/mujoco.py
coker/toolkits/kinematics/rigid_body.py
coker/toolkits/kinematics/visualiser.py
coker/toolkits/spatial/__init__.py
coker/toolkits/spatial/algebra.py
coker/toolkits/spatial/types.py
coker/toolkits/spatial/unit_quaternion.py
coker/toolkits/system_modelling/__init__.py
coker/toolkits/system_modelling/api.py
coker/toolkits/system_modelling/modelling/__init__.py
coker/toolkits/system_modelling/modelling/coker_abc.py
coker/toolkits/system_modelling/projects/__init__.py
coker/toolkits/system_modelling/std_lib/__init__.py
coker/toolkits/system_modelling/std_lib/common/__init__.py
coker/toolkits/system_modelling/std_lib/common/signal_processing.py
coker-0.3.14.dist-info/licenses/LICENSE.TXT
coker-0.3.14.dist-info/METADATA
coker-0.3.14.dist-info/WHEEL
coker-0.3.14.dist-info/RECORD
