Metadata-Version: 2.4
Name: coker
Version: 0.3.14
Summary: Coker Mathematical Programming Toolkit
License-Expression: MPL-2.0
License-File: LICENSE.TXT
Author: Peter Cudmore
Author-email: drpetercudmore@gmail.com
Maintainer: Peter Cudmore
Maintainer-email: drpetercudmore@gmail.com
Requires-Python: >=3.10
Classifier: Development Status :: 3 - Alpha
Classifier: Intended Audience :: Developers
Classifier: Topic :: Software Development :: Build Tools
Classifier: Programming Language :: Python
Provides-Extra: dev
Requires-Dist: black (==25.1.0) ; extra == "dev"
Requires-Dist: mypy ; extra == "dev"
Requires-Dist: numpy (>=2)
Requires-Dist: pytest ; extra == "dev"
Requires-Dist: pytest-mypy ; extra == "dev"
Requires-Dist: scipy
Requires-Dist: sympy
Requires-Dist: typing-extensions
